email_signature_detector/__init__.py
email_signature_detector/predictor.py
email_signature_detector/utils.py
email_signature_detector/model/__init__.py
email_signature_detector/model/tokenizer/special_tokens_map.json
email_signature_detector/model/tokenizer/tokenizer.json
email_signature_detector/model/tokenizer/tokenizer_config.json
email_signature_detector-0.1.11.dist-info/licenses/LICENSE
email_signature_detector-0.1.11.dist-info/METADATA
email_signature_detector-0.1.11.dist-info/WHEEL
email_signature_detector-0.1.11.dist-info/top_level.txt
email_signature_detector-0.1.11.dist-info/RECORD
