Metadata-Version: 2.4
Name: email_signature_detector
Version: 0.1.11
Summary: A library to predict email signatures using an ONNX model.
Home-page: https://github.com/numeo-ai/email-signature-detector
Author: Numeo AI Team
Author-email: team@numeo.ai
License-File: LICENSE
Requires-Dist: numpy
Requires-Dist: onnxruntime
Requires-Dist: transformers
Requires-Dist: torch
Dynamic: author
Dynamic: author-email
Dynamic: description
Dynamic: description-content-type
Dynamic: home-page
Dynamic: license-file
Dynamic: requires-dist
Dynamic: summary
